arroyopy/__init__.py
arroyopy/files.py
arroyopy/listener.py
arroyopy/operator.py
arroyopy/publisher.py
arroyopy/redis.py
arroyopy/schemas.py
arroyopy/timing.py
arroyopy/zmq.py
arroyopy/app/__init__.py
arroyopy/app/redis_file_watcher.py
arroyopy-0.2.2.dist-info/METADATA
arroyopy-0.2.2.dist-info/WHEEL
arroyopy-0.2.2.dist-info/entry_points.txt
arroyopy-0.2.2.dist-info/licenses/LICENSE
arroyopy-0.2.2.dist-info/RECORD
