Metadata-Version: 2.4
Name: arroyopy
Version: 0.2.2
Summary: A library to simplify processing streams of data
Project-URL: Homepage, https://github.com/als-computing/arroyopy
Project-URL: Issues, https://github.com/als-computing/arroyopy/issues
Author-email: Dylan McReynolds <dmcreynolds@lbl.gov>
License: BSD-3
License-File: LICENSE
Classifier: Operating System :: OS Independent
Classifier: Programming Language :: Python :: 3
Requires-Python: <3.13,>=3.11
Requires-Dist: numpy
Requires-Dist: pandas
Requires-Dist: pydantic>=2.0
Requires-Dist: python-dotenv
Requires-Dist: typer
Provides-Extra: dev
Requires-Dist: fakeredis; extra == 'dev'
Requires-Dist: flake8; extra == 'dev'
Requires-Dist: pre-commit; extra == 'dev'
Requires-Dist: pytest-asyncio; extra == 'dev'
Requires-Dist: pytest-mock; extra == 'dev'
Requires-Dist: pyzmq; extra == 'dev'
Requires-Dist: redis; extra == 'dev'
Requires-Dist: tiled[minimal-server]; extra == 'dev'
Requires-Dist: typer; extra == 'dev'
Provides-Extra: file-watch
Requires-Dist: watchfiles>=0.21.0; extra == 'file-watch'
Provides-Extra: redis
Requires-Dist: redis; extra == 'redis'
Provides-Extra: tiled
Requires-Dist: tiled[client]; extra == 'tiled'
Provides-Extra: zmq
Requires-Dist: pyzmq; extra == 'zmq'
